setup.py
imgcaption/__init__.py
imgcaption/imgcaption.py
imgcaption.egg-info/PKG-INFO
imgcaption.egg-info/SOURCES.txt
imgcaption.egg-info/dependency_links.txt
imgcaption.egg-info/not-zip-safe
imgcaption.egg-info/requires.txt
imgcaption.egg-info/top_level.txt