Metadata-Version: 1.0
Name: imgcaption
Version: 0.1.2
Summary: Library that gets image captions using Microsoft's https://www.captionbot.ai/
Home-page: https://github.com/DeanF/imgcaption
Author: DeanF
Author-email: UNKNOWN
License: UNKNOWN
Platform: UNKNOWN
